particle_system/__init__.py
particle_system/particle.py
particle_system/particle_generator.py
particle_system/particle_system.py
particle_system/particle_tester.py
src/__init__.py
src/particle.py
src/particle_system.py
src/particle_system/__init__.py
src/particle_system/particle.py
src/particle_system/particle_system.py
particle_systemszcz-1.4.0.dist-info/METADATA
particle_systemszcz-1.4.0.dist-info/WHEEL
particle_systemszcz-1.4.0.dist-info/top_level.txt
particle_systemszcz-1.4.0.dist-info/RECORD
