Metadata-Version: 2.2
Name: particle_systemszcz
Version: 1.4.0
Summary: A particle system library
Home-page: https://github.com/rutra8002/particle_system
Author: rutra
Author-email: ruterszcz@gmail.com
Classifier: Programming Language :: Python :: 3
Classifier: Operating System :: OS Independent
Requires-Python: >=3.6
Requires-Dist: pygame-ce
Requires-Dist: pygame-gui
Dynamic: author
Dynamic: author-email
Dynamic: classifier
Dynamic: description
Dynamic: description-content-type
Dynamic: home-page
Dynamic: requires-dist
Dynamic: requires-python
Dynamic: summary
